pyqt_rounded_corners_lineedit/__init__.py
pyqt_rounded_corners_lineedit/roundedCornersLineEdit.py
pyqt_rounded_corners_lineedit/style/__init__.py
pyqt_rounded_corners_lineedit/style/lineedit.css
pyqt_rounded_corners_lineedit-0.0.11.dist-info/LICENSE
pyqt_rounded_corners_lineedit-0.0.11.dist-info/METADATA
pyqt_rounded_corners_lineedit-0.0.11.dist-info/WHEEL
pyqt_rounded_corners_lineedit-0.0.11.dist-info/top_level.txt
pyqt_rounded_corners_lineedit-0.0.11.dist-info/RECORD
