Metadata-Version: 2.1
Name: pyqt-rounded-corners-lineedit
Version: 0.0.11
Summary: PyQt QLineEdit with rounded corners
Home-page: https://github.com/yjg30737/pyqt-rounded-corners-lineedit.git
Author: Jung Gyu Yoon
Author-email: yjg30737@gmail.com
License: MIT
Platform: UNKNOWN
License-File: LICENSE
Requires-Dist: PyQt5 (>=5.8)
Requires-Dist: absresgetter (>=0.0.1)
